Workbook

Sheet Budget_Reel
A1: Mois | B1: Poste | C1: Nature | D1: Budget_EUR | E1: Reel_EUR | F1: Ecart_EUR | G1: Ecart_pct
A2: 2025-01 | B2: Chiffre d'affaires | C2: Produit | D2: 26400 | E2: 26380.77 | F2: =E2-D2 | G2: =IFERROR(F2/D2,0)
A3: 2025-01 | B3: Achats marchandises | C3: Charge variable | D3: 11000 | E3: 11719.5 | F3: =E3-D3 | G3: =IFERROR(F3/D3,0)
A4: 2025-01 | B4: Salaires et charges | C4: Charge fixe | D4: 5456 | E4: 5352.49 | F4: =E4-D4 | G4: =IFERROR(F4/D4,0)
A5: 2025-01 | B5: Loyer et charges locatives | C5: Charge fixe | D5: 1584 | E5: 1650.26 | F5: =E5-D5 | G5: =IFERROR(F5/D5,0)
A6: 2025-01 | B6: Marketing | C6: Charge semi-variable | D6: 1056 | E6: 1044.47 | F6: =E6-D6 | G6: =IFERROR(F6/D6,0)
A7: 2025-01 | B7: Logistique | C7: Charge variable | D7: 792 | E7: 758.51 | F7: =E7-D7 | G7: =IFERROR(F7/D7,0)
A8: 2025-01 | B8: Autres charges | C8: Charge fixe | D8: 572 | E8: 577.47 | F8: =E8-D8 | G8: =IFERROR(F8/D8,0)
A9: 2025-02 | B9: Chiffre d'affaires | C9: Produit | D9: 27000 | E9: 27141.86 | F9: =E9-D9 | G9: =IFERROR(F9/D9,0)
A10: 2025-02 | B10: Achats marchandises | C10: Charge variable | D10: 11250 | E10: 11224.53 | F10: =E10-D10 | G10: =IFERROR(F10/D10,0)
A11: 2025-02 | B11: Salaires et charges | C11: Charge fixe | D11: 5580 | E11: 5740.98 | F11: =E11-D11 | G11: =IFERROR(F11/D11,0)
A12: 2025-02 | B12: Loyer et charges locatives | C12: Charge fixe | D12: 1620 | E12: 1620.69 | F12: =E12-D12 | G12: =IFERROR(F12/D12,0)
A13: 2025-02 | B13: Marketing | C13: Charge semi-variable | D13: 1080 | E13: 1234.5 | F13: =E13-D13 | G13: =IFERROR(F13/D13,0)
... A85: 2025-12 | B85: Autres charges | C85: Charge fixe | D85: 858 | E85: 864.8 | F85: =E85-D85 | G85: =IFERROR(F85/D85,0)

Sheet Synthese
A1: CONTRÔLE BUDGÉTAIRE - CAS SIMULÉ
A2: CA budgété | B2: =SUMIF(Budget_Reel!B2:B85,"Chiffre d'affaires",Budget_Reel!D2:D85)
A3: CA réel | B3: =SUMIF(Budget_Reel!B2:B85,"Chiffre d'affaires",Budget_Reel!E2:E85)
A4: Charges budgétées | B4: =SUM(Budget_Reel!D2:D85)-B2
A5: Charges réelles | B5: =SUM(Budget_Reel!E2:E85)-B3
A6: Résultat budgété simplifié | B6: =B2-B4
A7: Résultat réel simplifié | B7: =B3-B5
A8: Écart de résultat | B8: =B7-B6
A11: Résultat simplifié mensuel
A12: Mois | B12: CA budgété | C12: CA réel | D12: Charges budgétées | E12: Charges réelles | F12: Résultat budgété | G12: Résultat réel
A13: 2025-01 | B13: =SUMIFS(Budget_Reel!D$2:D$85,Budget_Reel!A$2:A$85,A13,Budget_Reel!B$2:B$85,"Chiffre d'affaires") | C13: =SUMIFS(Budget_Reel!E$2:E$85,Budget_Reel!A$2:A$85,A13,Budget_Reel!B$2:B$85,"Chiffre d'affaires") | D13: =SUMIFS(Budget_Reel!D$2:D$85,Budget_Reel!A$2:A$85,A13)-B13 | E13: =SUMIFS(Budget_Reel!E$2:E$85,Budget_Reel!A$2:A$85,A13)-C13 | F13: =B13-D13 | G13: =C13-E13
A14: 2025-02 | B14: =SUMIFS(Budget_Reel!D$2:D$85,Budget_Reel!A$2:A$85,A14,Budget_Reel!B$2:B$85,"Chiffre d'affaires") | C14: =SUMIFS(Budget_Reel!E$2:E$85,Budget_Reel!A$2:A$85,A14,Budget_Reel!B$2:B$85,"Chiffre d'affaires") | D14: =SUMIFS(Budget_Reel!D$2:D$85,Budget_Reel!A$2:A$85,A14)-B14 | E14: =SUMIFS(Budget_Reel!E$2:E$85,Budget_Reel!A$2:A$85,A14)-C14 | F14: =B14-D14 | G14: =C14-E14
A15: 2025-03 | B15: =SUMIFS(Budget_Reel!D$2:D$85,Budget_Reel!A$2:A$85,A15,Budget_Reel!B$2:B$85,"Chiffre d'affaires") | C15: =SUMIFS(Budget_Reel!E$2:E$85,Budget_Reel!A$2:A$85,A15,Budget_Reel!B$2:B$85,"Chiffre d'affaires") | D15: =SUMIFS(Budget_Reel!D$2:D$85,Budget_Reel!A$2:A$85,A15)-B15 | E15: =SUMIFS(Budget_Reel!E$2:E$85,Budget_Reel!A$2:A$85,A15)-C15 | F15: =B15-D15 | G15: =C15-E15
A16: 2025-04 | B16: =SUMIFS(Budget_Reel!D$2:D$85,Budget_Reel!A$2:A$85,A16,Budget_Reel!B$2:B$85,"Chiffre d'affaires") | C16: =SUMIFS(Budget_Reel!E$2:E$85,Budget_Reel!A$2:A$85,A16,Budget_Reel!B$2:B$85,"Chiffre d'affaires") | D16: =SUMIFS(Budget_Reel!D$2:D$85,Budget_Reel!A$2:A$85,A16)-B16 | E16: =SUMIFS(Budget_Reel!E$2:E$85,Budget_Reel!A$2:A$85,A16)-C16 | F16: =B16-D16 | G16: =C16-E16
A17: 2025-05 | B17: =SUMIFS(Budget_Reel!D$2:D$85,Budget_Reel!A$2:A$85,A17,Budget_Reel!B$2:B$85,"Chiffre d'affaires") | C17: =SUMIFS(Budget_Reel!E$2:E$85,Budget_Reel!A$2:A$85,A17,Budget_Reel!B$2:B$85,"Chiffre d'affaires") | D17: =SUMIFS(Budget_Reel!D$2:D$85,Budget_Reel!A$2:A$85,A17)-B17 | E17: =SUMIFS(Budget_Reel!E$2:E$85,Budget_Reel!A$2:A$85,A17)-C17 | F17: =B17-D17 | G17: =C17-E17
A18: 2025-06 | B18: =SUMIFS(Budget_Reel!D$2:D$85,Budget_Reel!A$2:A$85,A18,Budget_Reel!B$2:B$85,"Chiffre d'affaires") | C18: =SUMIFS(Budget_Reel!E$2:E$85,Budget_Reel!A$2:A$85,A18,Budget_Reel!B$2:B$85,"Chiffre d'affaires") | D18: =SUMIFS(Budget_Reel!D$2:D$85,Budget_Reel!A$2:A$85,A18)-B18 | E18: =SUMIFS(Budget_Reel!E$2:E$85,Budget_Reel!A$2:A$85,A18)-C18 | F18: =B18-D18 | G18: =C18-E18
A19: 2025-07 | B19: =SUMIFS(Budget_Reel!D$2:D$85,Budget_Reel!A$2:A$85,A19,Budget_Reel!B$2:B$85,"Chiffre d'affaires") | C19: =SUMIFS(Budget_Reel!E$2:E$85,Budget_Reel!A$2:A$85,A19,Budget_Reel!B$2:B$85,"Chiffre d'affaires") | D19: =SUMIFS(Budget_Reel!D$2:D$85,Budget_Reel!A$2:A$85,A19)-B19 | E19: =SUMIFS(Budget_Reel!E$2:E$85,Budget_Reel!A$2:A$85,A19)-C19 | F19: =B19-D19 | G19: =C19-E19
A20: 2025-08 | B20: =SUMIFS(Budget_Reel!D$2:D$85,Budget_Reel!A$2:A$85,A20,Budget_Reel!B$2:B$85,"Chiffre d'affaires") | C20: =SUMIFS(Budget_Reel!E$2:E$85,Budget_Reel!A$2:A$85,A20,Budget_Reel!B$2:B$85,"Chiffre d'affaires") | D20: =SUMIFS(Budget_Reel!D$2:D$85,Budget_Reel!A$2:A$85,A20)-B20 | E20: =SUMIFS(Budget_Reel!E$2:E$85,Budget_Reel!A$2:A$85,A20)-C20 | F20: =B20-D20 | G20: =C20-E20
A21: 2025-09 | B21: =SUMIFS(Budget_Reel!D$2:D$85,Budget_Reel!A$2:A$85,A21,Budget_Reel!B$2:B$85,"Chiffre d'affaires") | C21: =SUMIFS(Budget_Reel!E$2:E$85,Budget_Reel!A$2:A$85,A21,Budget_Reel!B$2:B$85,"Chiffre d'affaires") | D21: =SUMIFS(Budget_Reel!D$2:D$85,Budget_Reel!A$2:A$85,A21)-B21 | E21: =SUMIFS(Budget_Reel!E$2:E$85,Budget_Reel!A$2:A$85,A21)-C21 | F21: =B21-D21 | G21: =C21-E21
A22: 2025-10 | B22: =SUMIFS(Budget_Reel!D$2:D$85,Budget_Reel!A$2:A$85,A22,Budget_Reel!B$2:B$85,"Chiffre d'affaires") | C22: =SUMIFS(Budget_Reel!E$2:E$85,Budget_Reel!A$2:A$85,A22,Budget_Reel!B$2:B$85,"Chiffre d'affaires") | D22: =SUMIFS(Budget_Reel!D$2:D$85,Budget_Reel!A$2:A$85,A22)-B22 | E22: =SUMIFS(Budget_Reel!E$2:E$85,Budget_Reel!A$2:A$85,A22)-C22 | F22: =B22-D22 | G22: =C22-E22
A23: 2025-11 | B23: =SUMIFS(Budget_Reel!D$2:D$85,Budget_Reel!A$2:A$85,A23,Budget_Reel!B$2:B$85,"Chiffre d'affaires") | C23: =SUMIFS(Budget_Reel!E$2:E$85,Budget_Reel!A$2:A$85,A23,Budget_Reel!B$2:B$85,"Chiffre d'affaires") | D23: =SUMIFS(Budget_Reel!D$2:D$85,Budget_Reel!A$2:A$85,A23)-B23 | E23: =SUMIFS(Budget_Reel!E$2:E$85,Budget_Reel!A$2:A$85,A23)-C23 | F23: =B23-D23 | G23: =C23-E23
A24: 2025-12 | B24: =SUMIFS(Budget_Reel!D$2:D$85,Budget_Reel!A$2:A$85,A24,Budget_Reel!B$2:B$85,"Chiffre d'affaires") | C24: =SUMIFS(Budget_Reel!E$2:E$85,Budget_Reel!A$2:A$85,A24,Budget_Reel!B$2:B$85,"Chiffre d'affaires") | D24: =SUMIFS(Budget_Reel!D$2:D$85,Budget_Reel!A$2:A$85,A24)-B24 | E24: =SUMIFS(Budget_Reel!E$2:E$85,Budget_Reel!A$2:A$85,A24)-C24 | F24: =B24-D24 | G24: =C24-E24
